[{"season": "2008", "bowler": "Sohail Tanvir", "team": "Rajasthan Royals", "wickets": 22}, {"season": "2009", "bowler": "RP Singh", "team": "Deccan Chargers", "wickets": 23}, {"season": "2010", "bowler": "PP Ojha", "team": "Deccan Chargers", "wickets": 21}, {"season": "2011", "bowler": "SL Malinga", "team": "Mumbai Indians", "wickets": 28}, {"season": "2012", "bowler": "M Morkel", "team": "Delhi Daredevils", "wickets": 25}, {"season": "2013", "bowler": "DJ Bravo", "team": "Chennai Super Kings", "wickets": 32}, {"season": "2014", "bowler": "MM Sharma", "team": "Chennai Super Kings", "wickets": 23}, {"season": "2015", "bowler": "DJ Bravo", "team": "Chennai Super Kings", "wickets": 26}, {"season": "2016", "bowler": "B Kumar", "team": "Sunrisers Hyderabad", "wickets": 23}, {"season": "2017", "bowler": "B Kumar", "team": "Sunrisers Hyderabad", "wickets": 26}, {"season": "2018", "bowler": "AJ Tye", "team": "Kings XI Punjab", "wickets": 24}, {"season": "2019", "bowler": "Imran Tahir", "team": "Chennai Super Kings", "wickets": 26}, {"season": "2020", "bowler": "K Rabada", "team": "Delhi Capitals", "wickets": 32}, {"season": "2021", "bowler": "HV Patel", "team": "Royal Challengers Bangalore", "wickets": 32}, {"season": "2022", "bowler": "YS Chahal", "team": "Rajasthan Royals", "wickets": 27}, {"season": "2023", "bowler": "Mohammed Shami", "team": "Gujarat Titans", "wickets": 28}, {"season": "2024", "bowler": "HV Patel", "team": "Punjab Kings", "wickets": 24}, {"season": "2025", "bowler": "M Prasidh Krishna", "team": "Gujarat Titans", "wickets": 25}]